eve_arango/__init__.py
eve_arango/arangodb.py
eve_arango-0.3.3.dist-info/METADATA
eve_arango-0.3.3.dist-info/RECORD
eve_arango-0.3.3.dist-info/WHEEL
eve_arango-0.3.3.dist-info/top_level.txt
