Metadata-Version: 2.1
Name: eve-arango
Version: 0.3.3
Summary: Eve ArangoDB data layer
Home-page: https://github.com/tangram/eve-arango
Author: Eirik Krogstad
Author-email: eirikkr@gmail.com
License: MIT
Platform: UNKNOWN
Classifier: Development Status :: 3 - Alpha
Classifier: Intended Audience :: Developers
Classifier: License :: OSI Approved :: MIT License
Classifier: Programming Language :: Python
Classifier: Programming Language :: Python :: 3
Requires-Dist: Eve
Requires-Dist: python-arango
